{"cameraMode":{"drawMode":0,"name":"Shaded","section":"Shading Mode"},"sceneLighting":true,"audioPlay":false,"sceneViewState":{"showFog":true,"showMaterialUpdate":false,"showSkybox":true,"showFlares":true,"showImageEffects":true,"showParticleSystems":true},"in2DMode":false,"pivot":{"x":1.9875459671020508,"y":-1.33636474609375,"z":1.908989429473877},"rotation":{"x":0.31172555685043337,"y":-0.4957723021507263,"z":0.1965237557888031,"w":0.7863942384719849},"size":9.438447952270508,"orthographic":false}